certbot_dns_azure/__init__.py
certbot_dns_azure/_internal/__init__.py
certbot_dns_azure/_internal/dns_azure.py
certbot_dns_azure-2.6.1.dist-info/LICENSE.txt
certbot_dns_azure-2.6.1.dist-info/METADATA
certbot_dns_azure-2.6.1.dist-info/WHEEL
certbot_dns_azure-2.6.1.dist-info/entry_points.txt
certbot_dns_azure-2.6.1.dist-info/top_level.txt
certbot_dns_azure-2.6.1.dist-info/RECORD
