Metadata-Version: 2.1
Name: certbot-dns-azure
Version: 2.6.1
Summary: Azure DNS Authenticator plugin for Certbot
Home-page: https://github.com/terricain/certbot-dns-azure
Author: Terri Cain
Author-email: terri@dolphincorp.co.uk
License: Apache License 2.0
Classifier: Development Status :: 5 - Production/Stable
Classifier: Environment :: Plugins
Classifier: Intended Audience :: System Administrators
Classifier: License :: OSI Approved :: Apache Software License
Classifier: Operating System :: POSIX :: Linux
Classifier: Programming Language :: Python
Classifier: Programming Language :: Python :: 3
Classifier: Programming Language :: Python :: 3.11
Classifier: Programming Language :: Python :: 3.12
Classifier: Topic :: Internet :: WWW/HTTP
Classifier: Topic :: Security
Classifier: Topic :: System :: Installation/Setup
Classifier: Topic :: System :: Networking
Classifier: Topic :: System :: Systems Administration
Classifier: Topic :: Utilities
Requires-Python: >=3.6
License-File: LICENSE.txt
Requires-Dist: azure-identity>=1.19.0
Requires-Dist: azure-mgmt-dns>=8.2.0
Requires-Dist: azure-core>=1.32.0
Requires-Dist: setuptools>=41.6.0
Requires-Dist: certbot<4.0,>=3.0
Provides-Extra: docs
Requires-Dist: Sphinx>=1.0; extra == "docs"
Requires-Dist: sphinx_rtd_theme; extra == "docs"
